fluidra/__init__.py
fluidra/elements.py
fluidra-1.0.0.dist-info/METADATA
fluidra-1.0.0.dist-info/WHEEL
fluidra-1.0.0.dist-info/top_level.txt
fluidra-1.0.0.dist-info/RECORD
