Metadata-Version: 2.1
Name: fluidra
Version: 1.0.0
Summary: Fluidra Webtouch Automation Package
Author: Anthony Kahley
Author-email: akahley@fluidra.com
Keywords: fluidra,automation,test
Classifier: Development Status :: 1 - Planning
Classifier: Intended Audience :: Developers
Classifier: Programming Language :: Python :: 3
Classifier: Operating System :: Unix
Classifier: Operating System :: MacOS :: MacOS X
Classifier: Operating System :: Microsoft :: Windows
Requires-Dist: selenium
